CHANGELOG
LICENSE
MANIFEST.in
README.rst
django_pickling.py
setup.py
django_pickling.egg-info/PKG-INFO
django_pickling.egg-info/SOURCES.txt
django_pickling.egg-info/dependency_links.txt
django_pickling.egg-info/pbr.json
django_pickling.egg-info/requires.txt
django_pickling.egg-info/top_level.txt